lucid_schemas/__init__.py
lucid_schemas/agent.py
lucid_schemas/api_evidence.py
lucid_schemas/app_deployment.py
lucid_schemas/app_registry.py
lucid_schemas/attestation.py
lucid_schemas/audit_chain.py
lucid_schemas/auditor.py
lucid_schemas/claim.py
lucid_schemas/constants.py
lucid_schemas/dashboard.py
lucid_schemas/dashboard_appraisal.py
lucid_schemas/enums.py
lucid_schemas/environment.py
lucid_schemas/evaluation.py
lucid_schemas/evidence.py
lucid_schemas/interaction_receipt.py
lucid_schemas/location.py
lucid_schemas/otel.py
lucid_schemas/pagination.py
lucid_schemas/passport_display.py
lucid_schemas/policy.py
lucid_schemas/reference_values.py
lucid_schemas/security.py
lucid_schemas/serverless.py
lucid_schemas/session.py
lucid_schemas/tenant_app.py
lucid_schemas/user.py
lucid_schemas/versioned.py
lucid_schemas/zk.py
lucid_sdk/__init__.py
lucid_sdk/auditor.py
lucid_sdk/base_auditor.py
lucid_sdk/client.py
lucid_sdk/exceptions.py
lucid_sdk/lpl_parser.py
lucid_sdk/persistence.py
lucid_sdk/policies.py
lucid_sdk/policy_engine.py
lucid_sdk/resilience.py
lucid_sdk/interfaces/__init__.py
lucid_sdk/interfaces/core.py
lucid_sdk/interfaces/services.py
lucid_sdk/providers/attestation.py
lucid_sdk/zk/__init__.py
lucid_sdk/zk/circuit.py
lucid_sdk/zk/evidence.py
lucid_sdk/zk/exceptions.py
lucid_sdk/zk/proof.py
lucid_sdk-1.0.0.dist-info/METADATA
lucid_sdk-1.0.0.dist-info/WHEEL
lucid_sdk-1.0.0.dist-info/top_level.txt
lucid_sdk-1.0.0.dist-info/RECORD
