Metadata-Version: 2.4
Name: lucid-sdk
Version: 1.0.0
Summary: Auditor SDK for the Lucid Computing platform
Author: Lucid Team
Project-URL: Repository, https://github.com/Lucid-Computing/lucid-monorepo
Project-URL: Homepage, https://github.com/Lucid-Computing/lucid-monorepo/tree/main/packages/lucid-sdk
Classifier: Development Status :: 4 - Beta
Classifier: Intended Audience :: Developers
Classifier: Programming Language :: Python :: 3
Classifier: Programming Language :: Python :: 3.12
Requires-Python: >=3.12
Requires-Dist: pydantic
Requires-Dist: cryptography
Requires-Dist: requests
Requires-Dist: httpx
Requires-Dist: structlog
Requires-Dist: tenacity
Requires-Dist: email-validator>=2.0.0
